sprm/__init__.py
sprm/cross_validation/__init__.py
sprm/cross_validation/_cv_support_functions.py
sprm/plot/__init__.py
sprm/plot/sprm_plot.py
sprm/preprocessing/__init__.py
sprm/preprocessing/_gsspp_utils.py
sprm/preprocessing/_preproc_utilities.py
sprm/preprocessing/gsspp.py
sprm/preprocessing/robcent.py
sprm/sprm/__init__.py
sprm/sprm/_m_support_functions.py
sprm/sprm/rm.py
sprm/sprm/snipls.py
sprm/sprm/sprm.py
sprm-0.7.1.dist-info/LICENSE
sprm-0.7.1.dist-info/METADATA
sprm-0.7.1.dist-info/WHEEL
sprm-0.7.1.dist-info/top_level.txt
sprm-0.7.1.dist-info/RECORD
